unifi_client/__init__.py
unifi_client/client.py
unifi_client-0.0.1.2.dist-info/LICENSE
unifi_client-0.0.1.2.dist-info/METADATA
unifi_client-0.0.1.2.dist-info/WHEEL
unifi_client-0.0.1.2.dist-info/top_level.txt
unifi_client-0.0.1.2.dist-info/RECORD
