Metadata-Version: 2.1
Name: unifi-client
Version: 0.0.1.2
Summary: Ubiquiti Unifi REST API Client.
Home-page: https://github.com/Selfnet/unifi_client
Author: Marcel Fest
Author-email: marcelf@selfnet.de
License: MIT
Keywords: metric prometheus unifi ubnt ubiquiti ap access point
Platform: UNKNOWN
Classifier: Development Status :: 4 - Beta
Classifier: Intended Audience :: Developers
Classifier: License :: OSI Approved :: MIT License
Classifier: Programming Language :: Python :: 3
Requires-Dist: requests
Provides-Extra: dev
Requires-Dist: pylint; extra == 'dev'
Requires-Dist: autopep8; extra == 'dev'
Requires-Dist: pep8; extra == 'dev'
Requires-Dist: PySocks; extra == 'dev'
Provides-Extra: socks
Requires-Dist: PySocks; extra == 'socks'
